mnistusps/__init__.py
mnistusps/split.py
mnistusps-0.1.0.dist-info/LICENSE
mnistusps-0.1.0.dist-info/METADATA
mnistusps-0.1.0.dist-info/WHEEL
mnistusps-0.1.0.dist-info/top_level.txt
mnistusps-0.1.0.dist-info/RECORD
