Metadata-Version: 2.1
Name: mnistusps
Version: 0.1.0
Summary: Revised splits for MNIST-USPS domain adaptation experiments
Home-page: https://github.com/LukasHedegaard/mnist-usps
Author: Lukas Hedegaard
License: UNKNOWN
Platform: UNKNOWN
Requires-Python: >=3.6
Requires-Dist: datasetops (==0.0.6)
Requires-Dist: requests
Requires-Dist: torchvision
Provides-Extra: build
Requires-Dist: setuptools ; extra == 'build'
Requires-Dist: wheel ; extra == 'build'
Requires-Dist: twine ; extra == 'build'
Provides-Extra: tests
Requires-Dist: pytest ; extra == 'tests'
Requires-Dist: pytest-cov ; extra == 'tests'
